securelib/__init__.py
securelib/attack_utils.py
securelib/digital_signature.py
securelib/encryption_utils.py
securelib/file_monitor_utils.py
securelib/file_utils.py
securelib/firewall_utils.py
securelib/hash_cracker.py
securelib/hash_utils.py
securelib/log_utils.py
securelib/network_utils.py
securelib/password_utils.py
securelib/vulnerability_scanner.py
securelib/xss_detector.py
securelib-1.1.5.dist-info/METADATA
securelib-1.1.5.dist-info/WHEEL
securelib-1.1.5.dist-info/top_level.txt
securelib-1.1.5.dist-info/RECORD
